fnphat/__init__.py
fnphat/cityweather/cityweather.py
fnphat/cityweather/__init__.py
fnphat.cityweather-0.0.5.dist-info/DESCRIPTION.rst
fnphat.cityweather-0.0.5.dist-info/METADATA
fnphat.cityweather-0.0.5.dist-info/metadata.json
fnphat.cityweather-0.0.5.dist-info/RECORD
fnphat.cityweather-0.0.5.dist-info/top_level.txt
fnphat.cityweather-0.0.5.dist-info/WHEEL
