Metadata-Version: 2.0
Name: fnphat.cityweather
Version: 0.0.5
Summary: Get the weather of a canadian city.
Home-page: https://github.com/fnphat/cityweather
Author: fnphat
Author-email: fnphat@gmail.com
License: MIT
Platform: UNKNOWN
Requires-Dist: arrow (>=0.6.0)
Requires-Dist: data-gc-ca-api (>=0.2.4)
